deephaven/theme_pack/__init__.py
deephaven/theme_pack/_register.py
deephaven/theme_pack/_js/LICENSE
deephaven/theme_pack/_js/README.md
deephaven/theme_pack/_js/example-theme-palette.jpg
deephaven/theme_pack/_js/example-theme.jpg
deephaven/theme_pack/_js/package.json
deephaven/theme_pack/_js/tsconfig.json
deephaven/theme_pack/_js/vite.config.ts
deephaven/theme_pack/_js/dist/index.js
deephaven/theme_pack/_js/src/index.ts
deephaven/theme_pack/_js/src/theme.css
deephaven/theme_pack/_js/src/vite-env.d.ts
js/README.md
deephaven_plugin_theme_pack-0.1.2.dist-info/METADATA
deephaven_plugin_theme_pack-0.1.2.dist-info/WHEEL
deephaven_plugin_theme_pack-0.1.2.dist-info/entry_points.txt
deephaven_plugin_theme_pack-0.1.2.dist-info/top_level.txt
deephaven_plugin_theme_pack-0.1.2.dist-info/RECORD
